python_project_template_anthony/__init__.py
python_project_template_anthony/main.py
python_project_template_anthony-0.1.2.dist-info/LICENSE
python_project_template_anthony-0.1.2.dist-info/METADATA
python_project_template_anthony-0.1.2.dist-info/WHEEL
python_project_template_anthony-0.1.2.dist-info/top_level.txt
python_project_template_anthony-0.1.2.dist-info/RECORD
